<?xml version="1.0" encoding="UTF-8"?>

<fmiModelDescription
  fmiVersion="3.0"
  modelName="MySteering_FMU"
  instantiationToken="{30f527c3-1513-4d04-ad18-f38360212319}"
  description="CarMaker Example of a FMI3.0 Steering FMU">

<CoSimulation
    modelIdentifier = "MySteering_FMU"
    canHandleVariableCommunicationStepSize = "true"
    providesIntermediateUpdate="false"
    canReturnEarlyAfterIntermediateUpdate="false">
</CoSimulation>

<UnitDefinitions>
  <Unit name="Nm">
    <BaseUnit kg="1" m="2" s="-2" factor="1" offset="0"/>
  </Unit>
  <Unit name="N">
    <BaseUnit kg="1" m="1" s="-2" factor="1" offset="0"/>
  </Unit>
  <Unit name="Ns/m">
    <BaseUnit kg="1" s="-1" factor="1" offset="0"/>
  </Unit>
  <Unit name="rad/s">
    <BaseUnit rad="1" s="-1" factor="1" offset="0"/>
  </Unit>
  <Unit name="rad/s2">
    <BaseUnit rad="1" s="-2" factor="1" offset="0"/>
  </Unit>
  <Unit name="m/s">
    <BaseUnit m="1" s="-1" factor="1" offset="0"/>
  </Unit>
  <Unit name="m/s2">
    <BaseUnit m="1" s="-2" factor="1" offset="0"/>
  </Unit>
</UnitDefinitions>

<ModelVariables>
  <Float64 name="iRack2StWhl" valueReference="1" causality = "parameter" variability="fixed" initial="exact" start="100.0"/>
  <Float64 name="Irot" valueReference="2" causality = "parameter" variability="fixed" initial="exact" unit="kg" start="0.001"/>
  <Float64 name="d" valueReference="3" causality = "parameter" variability="fixed" initial="exact" unit="Ns/m" start="0.1"/>
  <Float64 name="RackRange_0" valueReference="4" causality = "parameter" variability="fixed" initial="exact" unit="m" start="-0.07"/>
  <Float64 name="RackRange_1" valueReference="5" causality = "parameter" variability="fixed" initial="exact" unit="m" start="0.07"/>
  <Float64 name="TrqAmplify" valueReference="6" causality = "parameter" variability="fixed" initial="exact" start="3.0"/>
  <Float64 name="L_Inert"  valueReference="7" causality = "input" unit="kg" start="0.0"/>
  <Float64 name="R_Inert"  valueReference="8" causality = "input" unit="kg" start="0.0"/>
  <Float64 name="L_Frc"  valueReference="9" causality = "input" unit="N" start="0.0"/>
  <Float64 name="R_Frc"  valueReference="10" causality = "input" unit="N" start="0.0"/>
  <Float64 name="Trq_In"  valueReference="11" causality = "input" unit="Nm" start="0.0"/>
  <Float64 name="PosSign" valueReference="12" causality = "input" start="0.0"/>
  <Float64 name="TrqStatic" valueReference="13" causality = "output" unit="Nm" variability="continuous" start="0.0"/>
  <Float64 name="L_iSteer2q" valueReference="14" causality = "output" variability="continuous" start="0.0"/>
  <Float64 name="R_iSteer2q" valueReference="15" causality = "output" variability="continuous" start="0.0"/>
  <Float64 name="L_q" valueReference="16" causality = "output" variability="continuous" unit="m" start="0.0"/>
  <Float64 name="L_qp" valueReference="17" causality = "output" variability="continuous" unit="m/s" start="0.0"/>
  <Float64 name="L_qpp" valueReference="18" causality = "output" variability="continuous" unit="m/s2" start="0.0"/>
  <Float64 name="R_q" valueReference="19" causality = "output" variability="continuous" unit="m" start="0.0"/>
  <Float64 name="R_qp" valueReference="20" causality = "output" variability="continuous" unit="m/s" start="0.0"/>
  <Float64 name="R_qpp" valueReference="21" causality = "output" variability="continuous" unit="m/s2" start="0.0"/>
  <Float64 name="Ang" valueReference="22" causality = "output" variability="continuous" unit="rad" start="0.0"/>
  <Float64 name="AngVel" valueReference="23" causality = "output" variability="continuous" unit="rad/s" start="0.0"/>
  <Float64 name="AngAcc" valueReference="24" causality = "output" variability="continuous" unit="rad/s2" start="0.0"/>
  <Float64 name="Trq" valueReference="11" causality = "output" variability="continuous" unit="Nm" start="0.0"/>
</ModelVariables>

<ModelStructure>
  <Output valueReference="13"/>
  <Output valueReference="14"/>
  <Output valueReference="15"/>
  <Output valueReference="16"/>
  <Output valueReference="17"/>
  <Output valueReference="18"/>
  <Output valueReference="19"/>
  <Output valueReference="20"/>
  <Output valueReference="21"/>
  <Output valueReference="22"/>
  <Output valueReference="23"/>
  <Output valueReference="24"/>
</ModelStructure>


</fmiModelDescription>
